CHANGELOG.md
shuncommands/pdftool.py
shuncommands/rmtmp.py
shuncommands-1.0.10.dist-info/LICENSE
shuncommands-1.0.10.dist-info/METADATA
shuncommands-1.0.10.dist-info/WHEEL
shuncommands-1.0.10.dist-info/entry_points.txt
shuncommands-1.0.10.dist-info/RECORD
