Metadata-Version: 2.1
Name: shuncommands
Version: 1.0.10
Summary: mypaceshun usefull commands
Home-page: https://github.com/mypaceshun/shuncommands
License: MIT
Keywords: python,click
Author: KAWAI Shun
Author-email: mypaceshun@gmail.com
Maintainer: KAWAI Shun
Maintainer-email: mypaceshun@gmail.com
Requires-Python: >=3.8.1,<4.0
Classifier: License :: OSI Approved :: MIT License
Classifier: Programming Language :: Python :: 3
Classifier: Programming Language :: Python :: 3.9
Classifier: Programming Language :: Python :: 3.10
Classifier: Programming Language :: Python :: 3.11
Requires-Dist: click (>=8.1.7,<9.0.0)
Requires-Dist: gitignore-parser (>=0.1.6,<0.2.0)
Requires-Dist: pdfminer-six[pdf] (>=20221105,<20221106)
Requires-Dist: pikepdf[pdf] (>=8.4.0,<9.0.0)
Project-URL: Repository, https://github.com/mypaceshun/shuncommands
